sinapsis_ultralytics/__init__.py
sinapsis_ultralytics/helpers/__init__.py
sinapsis_ultralytics/helpers/params.py
sinapsis_ultralytics/helpers/tags.py
sinapsis_ultralytics/helpers/ultralytics_predict_helpers.py
sinapsis_ultralytics/templates/__init__.py
sinapsis_ultralytics/templates/ultralytics_base.py
sinapsis_ultralytics/templates/ultralytics_export.py
sinapsis_ultralytics/templates/ultralytics_predict.py
sinapsis_ultralytics/templates/ultralytics_train.py
sinapsis_ultralytics/templates/ultralytics_val.py
sinapsis_ultralytics-0.1.11.dist-info/licenses/LICENSE
sinapsis_ultralytics-0.1.11.dist-info/METADATA
sinapsis_ultralytics-0.1.11.dist-info/WHEEL
sinapsis_ultralytics-0.1.11.dist-info/top_level.txt
sinapsis_ultralytics-0.1.11.dist-info/RECORD
