Metadata-Version: 2.4
Name: sinapsis-ultralytics
Version: 0.1.11
Summary: Package to build computer vision applications based on the Ultralytics library
Author-email: SinapsisAI <dev@sinapsis-ai.com>
Project-URL: Homepage, https://sinapsis.tech
Project-URL: Documentation, https://docs.sinapsis.tech/docs
Project-URL: Tutorials, https://docs.sinapsis.tech/tutorials
Project-URL: Repository, https://github.com/Sinapsis-AI/sinapsis-object-detection.git
Requires-Python: >=3.10
License-File: LICENSE
Requires-Dist: sinapsis>=0.1.1
Requires-Dist: ultralytics>=8.3.88
Provides-Extra: sinapsis-data-visualization
Requires-Dist: sinapsis-data-visualization>=0.1.0; extra == "sinapsis-data-visualization"
Provides-Extra: all
Requires-Dist: sinapsis-ultralytics[sinapsis-data-readers,sinapsis-data-visualization,sinapsis-data-writers]; extra == "all"
Provides-Extra: sinapsis-data-writers
Requires-Dist: sinapsis-data-writers>=0.1.1; extra == "sinapsis-data-writers"
Provides-Extra: sinapsis-data-readers
Requires-Dist: sinapsis-data-readers>=0.1.2; extra == "sinapsis-data-readers"
Dynamic: license-file
